latex2unicode.py
md2tgmd.py
md2tgmd-0.3.10.dist-info/licenses/LICENSE
md2tgmd-0.3.10.dist-info/METADATA
md2tgmd-0.3.10.dist-info/WHEEL
md2tgmd-0.3.10.dist-info/top_level.txt
md2tgmd-0.3.10.dist-info/RECORD
