Metadata-Version: 2.4
Name: md2tgmd
Version: 0.3.10
Summary: md2tgmd is a Markdown to Telegram-specific-markdown converter.
License-File: LICENSE
Dynamic: description
Dynamic: description-content-type
Dynamic: license-file
Dynamic: summary
